OmeSliCC/BioSource.py
OmeSliCC/OmeSource.py
OmeSliCC/Omero.py
OmeSliCC/OmeroLabelReader.py
OmeSliCC/OmeroSource.py
OmeSliCC/PlainImageSource.py
OmeSliCC/TiffSource.py
OmeSliCC/XmlDict.py
OmeSliCC/ZarrSource.py
OmeSliCC/conversion.py
OmeSliCC/image_util.py
OmeSliCC/ome.py
OmeSliCC/omero_credentials.py
OmeSliCC/parameters.py
OmeSliCC/util.py
OmeSliCC-0.5.2.dist-info/LICENSE.md
OmeSliCC-0.5.2.dist-info/METADATA
OmeSliCC-0.5.2.dist-info/WHEEL
OmeSliCC-0.5.2.dist-info/top_level.txt
OmeSliCC-0.5.2.dist-info/RECORD
