Metadata-Version: 2.1
Name: OmeSliCC
Version: 0.5.2
Summary: Ome(ro) Slide Image Conversion and Compression pipeline
Author-email: Joost de Folter <folterj@gmail.com>
License: # OmeSliCC Licence Agreement
Project-URL: Homepage, https://github.com/FrancisCrickInstitute/OmeSliCC
License-File: LICENSE.md
Requires-Dist: numpy
Requires-Dist: pandas
Requires-Dist: scikit-image
Requires-Dist: scikit-learn
Requires-Dist: opencv-python
Requires-Dist: imagecodecs
Requires-Dist: numcodecs
Requires-Dist: tifffile
Requires-Dist: zarr
Requires-Dist: aiohttp
Requires-Dist: omero-py
Requires-Dist: ome-types
Requires-Dist: rsa
Requires-Dist: tqdm
Requires-Dist: psutil
Requires-Dist: PyYAML
Requires-Dist: Pillow
Requires-Dist: imageio
Requires-Dist: python-bioformats
Requires-Dist: xmltodict
Requires-Dist: matplotlib
Requires-Dist: validators
Requires-Dist: toml
